CryptNinja/__init__.py
CryptNinja/cryptomods.py
CryptNinja/customerror.py
CryptNinja/customlogger.py
CryptNinja/getfilename.py
CryptNinja/login.py
CryptNinja/purge.py
CryptNinja/sqllib.py
CryptNinja-0.0.0.dist-info/LICENSE.txt
CryptNinja-0.0.0.dist-info/METADATA
CryptNinja-0.0.0.dist-info/WHEEL
CryptNinja-0.0.0.dist-info/entry_points.txt
CryptNinja-0.0.0.dist-info/top_level.txt
CryptNinja-0.0.0.dist-info/RECORD
