Metadata-Version: 2.1
Name: CryptNinja
Version: 0.0.0
Summary: This is a next gen password safe which uses Key gen algos like argon hash.
Home-page: UNKNOWN
Author: Jayant Raizada
Author-email: jayantraizada1993@live.com
License: MIT
Platform: UNKNOWN
Classifier: Programming Language :: Python :: 3
Classifier: License :: OSI Approved :: MIT License
Classifier: Operating System :: OS Independent
Requires-Python: >=3.6
Requires-Dist: cryptography
Requires-Dist: argon2-cffi
Requires-Dist: tabulate
Requires-Dist: pycryptodome
